myFolder/my.py
myFolder-0.1.0.dist-info/METADATA
myFolder-0.1.0.dist-info/WHEEL
myFolder-0.1.0.dist-info/top_level.txt
myFolder-0.1.0.dist-info/RECORD
