Metadata-Version: 2.1
Name: myFolder
Version: 0.1.0
Summary: A example Python package
Home-page: UNKNOWN
Author: Sergey Efimov
Author-email: serg-2001200@mail.com
License: UNKNOWN
Platform: UNKNOWN
Requires: pandas
